{
    "data_paths": {
        "shapestacks": "/home/yuliu/Dataset/ShapeStacks",
        "birds": "/home/yuliu/Dataset/Birds",
        "dogs": "/home/yuliu/Dataset/Dogs",
        "cars": "/home/yuliu/Dataset/Cars",
        "clevrtex": "/home/yuliu/Dataset/CLEVRTEX",
        "ptr": "/home/yuliu/Dataset/PTR",
        "flowers": "/home/yuliu/Dataset/Flowers",
        "objectsroom": "/home/yuliu/Dataset/ObjectsRoom",
        "ycb": "/home/yuliu/Dataset/ObjectCentric/YCB",
        "scannet": "/home/yuliu/Dataset/ObjectCentric/ScanNet",
        "coco": "/home/yuliu/Dataset/ObjectCentric/COCO"
    },
    "log_path": "./results/"
}